BiGramGraph/__init__.py
BiGramGraph/analysis.py
BiGramGraph/core.py
BiGramGraph/exceptions.py
BiGramGraph/generator.py
BiGramGraph/py.typed
BiGramGraph/vectorizer.py
BiGramGraph/visualization.py
bigramgraph-2.1.0.dist-info/METADATA
bigramgraph-2.1.0.dist-info/WHEEL
bigramgraph-2.1.0.dist-info/licenses/LICENSE
bigramgraph-2.1.0.dist-info/RECORD
