Metadata-Version: 2.4
Name: BiGramGraph
Version: 2.1.0
Summary: Implementations of concepts presented in the paper 'On Bi Gram Graph attributes'
Project-URL: Homepage, https://github.com/MuteJester/BiGramGraph
Project-URL: Documentation, https://github.com/MuteJester/BiGramGraph#readme
Project-URL: Repository, https://github.com/MuteJester/BiGramGraph.git
Project-URL: Issues, https://github.com/MuteJester/BiGramGraph/issues
Author-email: Thomas Konstantinovsky <thomaskon90@gmail.com>, Matan Mizrachi <matt8ac@gmail.com>
License-Expression: MIT
License-File: LICENSE
Keywords: Graph Theory,Machine Learning,Metrics,NLP,Text Generation
Classifier: Development Status :: 4 - Beta
Classifier: Intended Audience :: Developers
Classifier: Intended Audience :: Science/Research
Classifier: License :: OSI Approved :: MIT License
Classifier: Programming Language :: Python :: 3
Classifier: Programming Language :: Python :: 3.11
Classifier: Programming Language :: Python :: 3.12
Classifier: Programming Language :: Python :: 3.13
Classifier: Topic :: Scientific/Engineering :: Artificial Intelligence
Classifier: Topic :: Text Processing :: Linguistic
Classifier: Typing :: Typed
Requires-Python: >=3.11
Requires-Dist: matplotlib>=3.7.0
Requires-Dist: networkx>=3.0
Requires-Dist: nltk>=3.8.0
Requires-Dist: numpy>=1.24.0
Requires-Dist: pandas>=2.0.0
Requires-Dist: pydot>=1.4.0
Requires-Dist: pyenchant>=3.2.0
Requires-Dist: pyvis>=0.3.0
Requires-Dist: scikit-learn>=1.2.0
Requires-Dist: seaborn>=0.12.0
Requires-Dist: spacy>=3.5.0
Requires-Dist: tqdm>=4.65.0
Requires-Dist: wordcloud>=1.9.0
Provides-Extra: dev
Requires-Dist: mypy>=1.0.0; extra == 'dev'
Requires-Dist: pre-commit>=3.0.0; extra == 'dev'
Requires-Dist: pytest-cov>=4.0.0; extra == 'dev'
Requires-Dist: pytest>=7.0.0; extra == 'dev'
Requires-Dist: ruff>=0.1.0; extra == 'dev'
